nb_config/__init__.py
nb_config/import_user_config.py
nb_config/nb_config_decorator.py
nb_config/simple_data_class.py
nb_config-1.4.dist-info/LICENSE
nb_config-1.4.dist-info/METADATA
nb_config-1.4.dist-info/WHEEL
nb_config-1.4.dist-info/top_level.txt
nb_config-1.4.dist-info/RECORD
