Metadata-Version: 2.1
Name: nb-config
Version: 1.4
Summary: 一个优雅的Python配置覆盖系统，基于继承机制让用户可以透明地覆盖第三方库的配置
Author-email: ydf <ydf0509@sohu.com>
Maintainer-email: ydf <ydf0509@sohu.com>
License: MIT
Project-URL: Homepage, https://github.com/ydf0509/nb_config
Project-URL: Repository, https://github.com/ydf0509/nb_config.git
Project-URL: Documentation, https://github.com/ydf0509/nb_config/wiki
Project-URL: Bug Tracker, https://github.com/ydf0509/nb_config/issues
Project-URL: Changelog, https://github.com/ydf0509/nb_config/blob/main/CHANGELOG.md
Keywords: config,configuration,override,third-party,library,settings,nb,inheritance
Classifier: Development Status :: 5 - Production/Stable
Classifier: Intended Audience :: Developers
Classifier: License :: OSI Approved :: MIT License
Classifier: Operating System :: OS Independent
Classifier: Programming Language :: Python :: 3
Classifier: Programming Language :: Python :: 3.6
Classifier: Programming Language :: Python :: 3.7
Classifier: Programming Language :: Python :: 3.8
Classifier: Programming Language :: Python :: 3.9
Classifier: Programming Language :: Python :: 3.10
Classifier: Programming Language :: Python :: 3.11
Classifier: Programming Language :: Python :: 3.12
Classifier: Programming Language :: Python :: 3.13
Classifier: Topic :: Software Development :: Libraries :: Python Modules
Classifier: Topic :: System :: Systems Administration
Classifier: Topic :: Utilities
Requires-Python: >=3.6
License-File: LICENSE
Requires-Dist: nb-log
